bleu.cp37-win_amd64.pyd
edit_distance.cp37-win_amd64.pyd
cyzil/__init__.py
cyzil/tokenizers.py
cyzil/cli/__init__.py
cyzil/cli/bleu_cli.py
cyzil/cli/edit_distance_cli.py
cyzil/cli/utils.py
cyzil-0.2.3.dist-info/LICENSE
cyzil-0.2.3.dist-info/METADATA
cyzil-0.2.3.dist-info/WHEEL
cyzil-0.2.3.dist-info/entry_points.txt
cyzil-0.2.3.dist-info/top_level.txt
cyzil-0.2.3.dist-info/RECORD
