Metadata-Version: 2.1
Name: cyzil
Version: 0.2.3
Summary: Computate metrics for machine translation
Home-page: https://github.com/box-key/cyzil
Author: Kei Nemoto, Kyle Gorman
Author-email: kei.nemoto28@gmail.com
License: Apache 2.0
Keywords: machine translation,natural language processing,seq2seq models,encoder-decoder models
Platform: UNKNOWN
Classifier: Programming Language :: Python :: 3 :: Only
Classifier: Programming Language :: Python :: 3.7
Classifier: License :: OSI Approved :: Apache Software License
Classifier: Operating System :: OS Independent
Classifier: Topic :: Scientific/Engineering :: Artificial Intelligence
Requires-Dist: Cython (>=0.29)
